bouillon/__init__.py
bouillon/bouillon.py
bouillon/cli.py
bouillon/git.py
bouillon/py.typed
bouillon-2.9.0.dist-info/LICENSE.txt
bouillon-2.9.0.dist-info/METADATA
bouillon-2.9.0.dist-info/WHEEL
bouillon-2.9.0.dist-info/entry_points.txt
bouillon-2.9.0.dist-info/top_level.txt
bouillon-2.9.0.dist-info/RECORD
