Metadata-Version: 2.1
Name: bouillon
Version: 2.9.0
Summary: Tool for releasing machine learning model and service projects and other fast paced python projects.
Author-email: Janus Heide <janusheide@gmail.com>
Project-URL: Homepage, https://github.com/janusheide/bouillon
Project-URL: Repository, https://github.com/janusheide/bouillon
Project-URL: Changelog, https://github.com/janusheide/bouillon/blob/main/NEWS.rst
Keywords: building,maintenance,utility
Classifier: Development Status :: 5 - Production/Stable
Classifier: Intended Audience :: Developers
Classifier: License :: OSI Approved :: BSD License
Classifier: Operating System :: MacOS
Classifier: Operating System :: Microsoft :: Windows
Classifier: Operating System :: POSIX
Classifier: Operating System :: Unix
Classifier: Programming Language :: Python :: 3.8
Classifier: Programming Language :: Python :: 3.9
Classifier: Programming Language :: Python :: 3.10
Classifier: Programming Language :: Python :: 3.11
Classifier: Programming Language :: Python :: 3.12
Classifier: Programming Language :: Python :: 3.13
Classifier: Programming Language :: Python :: Implementation :: CPython
Classifier: Programming Language :: Python :: Implementation :: PyPy
Classifier: Topic :: Scientific/Engineering :: Information Analysis
Classifier: Topic :: Software Development
Classifier: Topic :: Utilities
Classifier: Typing :: Typed
Requires-Python: >=3.8
License-File: LICENSE.txt
Requires-Dist: packaging>=22.0
Requires-Dist: tomli>=2.0.0; python_version < "3.11"
Provides-Extra: test
Requires-Dist: brundle==1.2.0; extra == "test"
Requires-Dist: dlister==1.2.0; extra == "test"
Requires-Dist: isort==5.13.2; extra == "test"
Requires-Dist: mypy==1.13.0; extra == "test"
Requires-Dist: ruff==0.8.1; extra == "test"
Requires-Dist: pytest==8.3.3; extra == "test"
Requires-Dist: pytest-cov<=6.0.0,>=5.0.0; extra == "test"
Provides-Extra: release
Requires-Dist: build==1.2.2.post1; extra == "release"
Requires-Dist: licensecheck==2024.3; extra == "release"
Requires-Dist: twine==5.1.1; extra == "release"
Provides-Extra: standard
Requires-Dist: bouillon[test]; extra == "standard"
Requires-Dist: bouillon[release]; extra == "standard"
Provides-Extra: dev
Requires-Dist: bouillon[standard]; extra == "dev"
Requires-Dist: uppd==1.5.0; extra == "dev"
